FINKER/__init__.py
FINKER/utils_Entropy.py
FINKER/utils_FINKER.py
FINKER/utils_SYNTHETIC_LIGHTCURVES.py
FINKER-1.0.1.dist-info/LICENSE
FINKER-1.0.1.dist-info/METADATA
FINKER-1.0.1.dist-info/WHEEL
FINKER-1.0.1.dist-info/top_level.txt
FINKER-1.0.1.dist-info/RECORD
