Metadata-Version: 2.1
Name: FINKER
Version: 1.0.1
Summary: A universal approach to optimal frequency identification using nonparametric kernel regression
Home-page: https://github.com/FiorenSt/FINKER
Author: Fiorenzo Stoppa
Author-email: f.stoppa@astro.ru.nl
Classifier: Programming Language :: Python :: 3
Classifier: License :: OSI Approved :: MIT License
Classifier: Operating System :: OS Independent
Requires-Python: >=3.6
License-File: LICENSE
Requires-Dist: numpy
Requires-Dist: scipy
Requires-Dist: matplotlib
Requires-Dist: scikit-learn
